README.txt
setup.py
pyoeis/__init__.py
pyoeis/client.py
pyoeis/errors.py
pyoeis/helpers.py
pyoeis/partialmethod.py
pyoeis/regex.py
pyoeis/sequence.py
pyoeis.egg-info/PKG-INFO
pyoeis.egg-info/SOURCES.txt
pyoeis.egg-info/dependency_links.txt
pyoeis.egg-info/requires.txt
pyoeis.egg-info/top_level.txt