Metadata-Version: 1.1
Name: pyoeis
Version: 1.1.4
Summary: Python interface to the OEIS
Home-page: www.physicynicism.com
Author: Dylan Evans
Author-email: dylan@physicynicism.com
License: UNKNOWN
Platform: UNKNOWN
Classifier: Development Status :: 3 - Alpha
Classifier: License :: OSI Approved :: Apache Software License
Classifier: Natural Language :: English
Classifier: Intended Audience :: Developers
Classifier: Topic :: Scientific/Engineering :: Mathematics
Classifier: Operating System :: OS Independent
Classifier: Programming Language :: Python
